{
    "code": 1,
    "message": "",
    "Data": {
        "WaitChooseTicketList": [
            {
                "SequenceID": "P81F001201812250001",
                "SerialID": "P81F0012018122514184010604121",
                "FormID": null,
                "FormName": "普通机票申请",
                "ApplyDateTime": "2018/12/25 下午 02:18:39",
                "ApplyName": "黃文毅",
                "StepName": "ADM簽核",
                "ToBeSignedID": null,
                "ToBeSignedName": null
            }
        ]
    }
}